.bumpversion.cfg
.cookiecutterrc
.coveragerc
.editorconfig
.travis.yml
AUTHORS.rst
CHANGELOG.rst
CONTRIBUTING.rst
LICENSE
MANIFEST.in
README.rst
setup.cfg
setup.py
tox.ini
ci/bootstrap.py
ci/templates/.travis.yml
docs/authors.rst
docs/changelog.rst
docs/conf.py
docs/contributing.rst
docs/index.rst
docs/installation.rst
docs/readme.rst
docs/requirements.txt
docs/spelling_wordlist.txt
docs/usage.rst
docs/reference/common_tasks.rst
docs/reference/index.rst
src/40wt_common_tasks.egg-info/PKG-INFO
src/40wt_common_tasks.egg-info/SOURCES.txt
src/40wt_common_tasks.egg-info/dependency_links.txt
src/40wt_common_tasks.egg-info/not-zip-safe
src/40wt_common_tasks.egg-info/requires.txt
src/40wt_common_tasks.egg-info/top_level.txt
src/common_tasks/__init__.py
tests/test_common_tasks.py